[{"community": "ALBANY PARK", "CAMERA ID": 1, "VIOLATIONS": 583317}, {"community": "ARCHER HEIGHTS", "CAMERA ID": 5, "VIOLATIONS": 200732}, {"community": "ASHBURN", "CAMERA ID": 7, "VIOLATIONS": 110479}, {"community": "AUBURN GRESHAM", "CAMERA ID": 4, "VIOLATIONS": 315604}, {"community": "AUSTIN", "CAMERA ID": 3, "VIOLATIONS": 310350}, {"community": "AVALON PARK", "CAMERA ID": 1, "VIOLATIONS": 34523}, {"community": "AVONDALE", "CAMERA ID": 3, "VIOLATIONS": 59681}, {"community": "BELMONT CRAGIN", "CAMERA ID": 9, "VIOLATIONS": 290758}, {"community": "BEVERLY", "CAMERA ID": 2, "VIOLATIONS": 64573}, {"community": "BRIDGEPORT", "CAMERA ID": 2, "VIOLATIONS": 37541}, {"community": "CALUMET HEIGHTS", "CAMERA ID": 1, "VIOLATIONS": 50697}, {"community": "CHICAGO LAWN", "CAMERA ID": 3, "VIOLATIONS": 409977}, {"community": "DUNNING", "CAMERA ID": 5, "VIOLATIONS": 296373}, {"community": "EAST GARFIELD PARK", "CAMERA ID": 4, "VIOLATIONS": 393071}, {"community": "EAST SIDE", "CAMERA ID": 4, "VIOLATIONS": 625780}, {"community": "EDGEWATER", "CAMERA ID": 1, "VIOLATIONS": 119710}, {"community": "EDISON PARK", "CAMERA ID": 1, "VIOLATIONS": 23410}, {"community": "FOREST GLEN", "CAMERA ID": 3, "VIOLATIONS": 141012}, {"community": "GAGE PARK", "CAMERA ID": 8, "VIOLATIONS": 206430}, {"community": "GREATER GRAND CROSSING", "CAMERA ID": 8, "VIOLATIONS": 420620}, {"community": "HUMBOLDT PARK", "CAMERA ID": 6, "VIOLATIONS": 353296}, {"community": "IRVING PARK", "CAMERA ID": 4, "VIOLATIONS": 481322}, {"community": "JEFFERSON PARK", "CAMERA ID": 3, "VIOLATIONS": 181720}, {"community": "LAKE VIEW", "CAMERA ID": 2, "VIOLATIONS": 47323}, {"community": "LINCOLN PARK", "CAMERA ID": 4, "VIOLATIONS": 295486}, {"community": "LINCOLN SQUARE", "CAMERA ID": 3, "VIOLATIONS": 140704}, {"community": "LOGAN SQUARE", "CAMERA ID": 3, "VIOLATIONS": 49814}, {"community": "LOOP", "CAMERA ID": 2, "VIOLATIONS": 105349}, {"community": "LOWER WEST SIDE", "CAMERA ID": 5, "VIOLATIONS": 145245}, {"community": "MCKINLEY PARK", "CAMERA ID": 3, "VIOLATIONS": 513463}, {"community": "MORGAN PARK", "CAMERA ID": 2, "VIOLATIONS": 62782}, {"community": "MOUNT GREENWOOD", "CAMERA ID": 1, "VIOLATIONS": 38792}, {"community": "NEAR NORTH SIDE", "CAMERA ID": 7, "VIOLATIONS": 228135}, {"community": "NEAR WEST SIDE", "CAMERA ID": 3, "VIOLATIONS": 376557}, {"community": "NEW CITY", "CAMERA ID": 3, "VIOLATIONS": 188849}, {"community": "NORTH CENTER", "CAMERA ID": 4, "VIOLATIONS": 268901}, {"community": "NORTH LAWNDALE", "CAMERA ID": 7, "VIOLATIONS": 812522}, {"community": "NORTH PARK", "CAMERA ID": 3, "VIOLATIONS": 707130}, {"community": "NORWOOD PARK", "CAMERA ID": 2, "VIOLATIONS": 98555}, {"community": "PORTAGE PARK", "CAMERA ID": 6, "VIOLATIONS": 764474}, {"community": "ROSELAND", "CAMERA ID": 2, "VIOLATIONS": 106588}, {"community": "SOUTH SHORE", "CAMERA ID": 2, "VIOLATIONS": 193982}, {"community": "UPTOWN", "CAMERA ID": 3, "VIOLATIONS": 355216}, {"community": "WASHINGTON PARK", "CAMERA ID": 2, "VIOLATIONS": 648997}, {"community": "WEST ELSDON", "CAMERA ID": 6, "VIOLATIONS": 46228}, {"community": "WEST ENGLEWOOD", "CAMERA ID": 1, "VIOLATIONS": 199192}, {"community": "WEST LAWN", "CAMERA ID": 1, "VIOLATIONS": 11928}, {"community": "WEST PULLMAN", "CAMERA ID": 1, "VIOLATIONS": 575203}, {"community": "WEST RIDGE", "CAMERA ID": 2, "VIOLATIONS": 385389}, {"community": "WEST TOWN", "CAMERA ID": 8, "VIOLATIONS": 348077}]